<annotation><filename>e0e1f1b503b31e67_3415-w500-h666-b0-p0-beach-style-bedroom.jpg</filename><folder>bedroom</folder><source><sourceImage>The MIT-CSAIL database of objects and scenes</sourceImage><sourceAnnotation>LabelMe Webtool</sourceAnnotation></source><object><name>window,large</name><deleted>0</deleted><verified>0</verified><parts><hasparts></hasparts><ispartof></ispartof></parts><date>12-May-2017 04:06:09</date><id>0</id><polygon><username>anonymous</username><pt><x>406</x><y>271</y></pt></polygon></object><object><name>floor,carpet</name><deleted>0</deleted><verified>0</verified><parts><hasparts></hasparts><ispartof></ispartof></parts><date>12-May-2017 04:07:08</date><id>1</id><polygon><username>anonymous</username><pt><x>103</x><y>609</y></pt></polygon></object><imagesize><nrows></nrows><ncols></ncols></imagesize></annotation>