<annotation><filename>f5015f430426c1c2_6904-w500-h666-b0-p0-traditional-bedroom.jpg</filename><folder>bedroom</folder><source><sourceImage>The MIT-CSAIL database of objects and scenes</sourceImage><sourceAnnotation>LabelMe Webtool</sourceAnnotation></source><object><name>lighting,chandeliers</name><deleted>0</deleted><verified>0</verified><parts><hasparts></hasparts><ispartof></ispartof></parts><date>12-May-2017 04:24:22</date><id>0</id><polygon><username>anonymous</username><pt><x>251</x><y>37</y></pt><pt><x>262</x><y>179</y></pt><pt><x>343</x><y>183</y></pt><pt><x>354</x><y>37</y></pt></polygon></object><object><name>window,small</name><deleted>0</deleted><verified>0</verified><parts><hasparts></hasparts><ispartof></ispartof></parts><date>12-May-2017 04:25:03</date><id>1</id><polygon><username>anonymous</username><pt><x>306</x><y>240</y></pt><pt><x>308</x><y>421</y></pt><pt><x>498</x><y>435</y></pt><pt><x>496</x><y>186</y></pt></polygon></object><imagesize><nrows></nrows><ncols></ncols></imagesize></annotation>