<annotation><filename>3a11dab804d4d0ae_4474-w500-h666-b0-p0-contemporary-bathroom.jpg</filename><folder>bathroom</folder><source><sourceImage>The MIT-CSAIL database of objects and scenes</sourceImage><sourceAnnotation>LabelMe Webtool</sourceAnnotation></source><object><name>shower,window_door</name><deleted>0</deleted><verified>0</verified><parts><hasparts></hasparts><ispartof></ispartof></parts><date>25-Jun-2017 00:57:36</date><id>0</id><type>bounding_box</type><polygon><username>anonymous</username><pt><x>436</x><y>3</y></pt><pt><x>637</x><y>3</y></pt><pt><x>637</x><y>460</y></pt><pt><x>436</x><y>460</y></pt></polygon></object><object><name>wallmaterial,painted</name><deleted>0</deleted><verified>0</verified><parts><hasparts></hasparts><ispartof></ispartof></parts><date>25-Jun-2017 00:57:45</date><id>1</id><type>bounding_box</type><polygon><username>anonymous</username><pt><x>223</x><y>44</y></pt><pt><x>255</x><y>44</y></pt><pt><x>255</x><y>143</y></pt><pt><x>223</x><y>143</y></pt></polygon></object><imagesize><nrows></nrows><ncols></ncols></imagesize></annotation>