<annotation><filename>a591ea92063284a2_3551-w500-h400-b0-p0-farmhouse-bathroom.jpg</filename><folder>bathroom</folder><source><sourceImage>The MIT-CSAIL database of objects and scenes</sourceImage><sourceAnnotation>LabelMe Webtool</sourceAnnotation></source><object><name>door,open</name><deleted>0</deleted><verified>0</verified><parts><hasparts/><ispartof/></parts><date>25-Jun-2017 01:05:15</date><id>0</id><type>bounding_box</type><polygon><username>anonymous</username><pt><x>216</x><y>76</y></pt><pt><x>357</x><y>76</y></pt><pt><x>357</x><y>419</y></pt><pt><x>216</x><y>419</y></pt></polygon></object><object><name>lighting,wall_lighting</name><deleted>0</deleted><verified>0</verified><parts><hasparts/><ispartof/></parts><date>25-Jun-2017 01:06:26</date><id>1</id><type>bounding_box</type><polygon><username>anonymous</username><pt><x>90</x><y>11</y></pt><pt><x>145</x><y>11</y></pt><pt><x>145</x><y>58</y></pt><pt><x>90</x><y>58</y></pt></polygon></object><imagesize><nrows></nrows><ncols></ncols></imagesize><object><name>door,closed</name><deleted>0</deleted><verified>0</verified><parts><hasparts/><ispartof/></parts><date>25-Jun-2017 01:52:10</date><id>2</id><type>bounding_box</type><polygon><username>anonymous</username><pt><x>395</x><y>79</y></pt><pt><x>521</x><y>79</y></pt><pt><x>521</x><y>412</y></pt><pt><x>395</x><y>412</y></pt></polygon></object><object><name>floor,laminate</name><deleted>0</deleted><verified>0</verified><parts><hasparts/><ispartof/></parts><date>25-Jun-2017 01:53:51</date><id>3</id><type>bounding_box</type><polygon><username>anonymous</username><pt><x>222</x><y>442</y></pt><pt><x>589</x><y>442</y></pt><pt><x>589</x><y>475</y></pt><pt><x>222</x><y>475</y></pt></polygon></object><object><name>wallmaterial,tile</name><deleted>0</deleted><verified>0</verified><parts><hasparts/><ispartof/></parts><date>25-Jun-2017 01:54:12</date><id>4</id><type>bounding_box</type><polygon><username>anonymous</username><pt><x>154</x><y>14</y></pt><pt><x>592</x><y>14</y></pt><pt><x>592</x><y>35</y></pt><pt><x>154</x><y>35</y></pt></polygon></object><object><name>sink,</name><deleted>0</deleted><verified>0</verified><parts><hasparts/><ispartof/></parts><date>26-Jun-2017 01:46:50</date><id>5</id><type>bounding_box</type><polygon><username>anonymous</username><pt><x>52</x><y>307</y></pt><pt><x>129</x><y>307</y></pt><pt><x>129</x><y>252</y></pt><pt><x>52</x><y>252</y></pt></polygon></object><object><name>window,small</name><deleted>0</deleted><verified>0</verified><parts><hasparts/><ispartof/></parts><date>26-Jun-2017 03:43:40</date><id>6</id><type>bounding_box</type><polygon><username>anonymous</username><pt><x>-2</x><y>22</y></pt><pt><x>28</x><y>22</y></pt><pt><x>28</x><y>282</y></pt><pt><x>-2</x><y>282</y></pt></polygon></object><object><name>bath_tub,</name><deleted>0</deleted><verified>0</verified><parts><hasparts/><ispartof/></parts><date>26-Jun-2017 03:45:21</date><id>7</id><type>bounding_box</type><polygon><username>anonymous</username><pt><x>567</x><y>312</y></pt><pt><x>639</x><y>312</y></pt><pt><x>639</x><y>478</y></pt><pt><x>567</x><y>478</y></pt></polygon></object><object><name>vanity,medium</name><deleted>0</deleted><verified>0</verified><parts><hasparts></hasparts><ispartof></ispartof></parts><date>26-Jun-2017 04:26:13</date><id>8</id><type>bounding_box</type><polygon><username>anonymous</username><pt><x>39</x><y>41</y></pt><pt><x>116</x><y>41</y></pt><pt><x>116</x><y>249</y></pt><pt><x>39</x><y>249</y></pt></polygon></object><object><name>wallmaterial,tile</name><deleted>0</deleted><verified>0</verified><parts><hasparts></hasparts><ispartof></ispartof></parts><date>26-Jun-2017 04:26:26</date><id>9</id><type>bounding_box</type><polygon><username>anonymous</username><pt><x>534</x><y>54</y></pt><pt><x>606</x><y>54</y></pt><pt><x>606</x><y>126</y></pt><pt><x>534</x><y>126</y></pt></polygon></object></annotation>