<annotation><filename>93119c1b07d04cbb_6128-w500-h400-b0-p0-transitional-bedroom.jpg</filename><folder>bedroom</folder><source><sourceImage>The MIT-CSAIL database of objects and scenes</sourceImage><sourceAnnotation>LabelMe Webtool</sourceAnnotation></source><object><name>wallcolor</name><deleted>0</deleted><verified>0</verified><parts><hasparts></hasparts><ispartof></ispartof></parts><date>25-Jun-2017 03:03:41</date><id>0</id><type>bounding_box</type><polygon><username>anonymous</username><pt><x>137</x><y>49</y></pt><pt><x>518</x><y>49</y></pt><pt><x>518</x><y>242</y></pt><pt><x>137</x><y>242</y></pt></polygon><attributes/><occluded/></object><object><name>wallcolor</name><deleted>0</deleted><verified>0</verified><parts><hasparts></hasparts><ispartof></ispartof></parts><date>25-Jun-2017 03:05:25</date><id>1</id><type>bounding_box</type><polygon><username>anonymous</username><pt><x>589</x><y>329</y></pt><pt><x>640</x><y>329</y></pt><pt><x>640</x><y>395</y></pt><pt><x>589</x><y>395</y></pt></polygon><attributes/><occluded/></object><object><name>baseboard,</name><deleted>1</deleted><verified>0</verified><parts><hasparts></hasparts><ispartof></ispartof></parts><date>25-Jun-2017 03:06:44</date><id>2</id><type>bounding_box</type><polygon><username>anonymous</username><pt><x>614</x><y>353</y></pt></polygon></object><imagesize><nrows></nrows><ncols></ncols></imagesize></annotation>