<annotation><filename>3591672907cb80e1_9813-w500-h400-b0-p0-contemporary-dining-room.jpg</filename><folder>dining</folder><source><sourceImage>The MIT-CSAIL database of objects and scenes</sourceImage><sourceAnnotation>LabelMe Webtool</sourceAnnotation></source><object><name>window,large</name><deleted>0</deleted><verified>0</verified><parts><hasparts/><ispartof/></parts><date>26-Jun-2017 04:04:05</date><id>0</id><type>bounding_box</type><polygon><username>anonymous</username><pt><x>5</x><y>8</y></pt><pt><x>159</x><y>8</y></pt><pt><x>159</x><y>356</y></pt><pt><x>5</x><y>356</y></pt></polygon></object><object><name>lighting,wall_lighting</name><deleted>0</deleted><verified>0</verified><parts><hasparts/><ispartof/></parts><date>26-Jun-2017 04:04:35</date><id>1</id><type>bounding_box</type><polygon><username>anonymous</username><pt><x>266</x><y>5</y></pt><pt><x>478</x><y>5</y></pt><pt><x>478</x><y>120</y></pt><pt><x>266</x><y>120</y></pt></polygon></object><imagesize><nrows></nrows><ncols></ncols></imagesize><object><name>ceiling,normal</name><deleted>0</deleted><verified>0</verified><parts><hasparts></hasparts><ispartof></ispartof></parts><date>26-Jun-2017 04:49:48</date><id>2</id><type>bounding_box</type><polygon><username>anonymous</username><pt><x>269</x><y>0</y></pt><pt><x>486</x><y>0</y></pt><pt><x>486</x><y>123</y></pt><pt><x>269</x><y>123</y></pt></polygon></object><object><name>wallmaterial,wood</name><deleted>0</deleted><verified>0</verified><parts><hasparts></hasparts><ispartof></ispartof></parts><date>26-Jun-2017 04:50:07</date><id>3</id><type>bounding_box</type><polygon><username>anonymous</username><pt><x>11</x><y>3</y></pt><pt><x>168</x><y>3</y></pt><pt><x>168</x><y>371</y></pt><pt><x>11</x><y>371</y></pt></polygon></object></annotation>