<annotation><filename>d9612b22079b77f6_9582-w500-h400-b0-p0-transitional-dining-room.jpg</filename><folder>dining</folder><source><sourceImage>The MIT-CSAIL database of objects and scenes</sourceImage><sourceAnnotation>LabelMe Webtool</sourceAnnotation></source><object><name>lighting,chandeliers</name><deleted>0</deleted><verified>0</verified><parts><hasparts></hasparts><ispartof></ispartof></parts><date>25-Jun-2017 05:14:59</date><id>0</id><type>bounding_box</type><polygon><username>anonymous</username><pt><x>131</x><y>47</y></pt><pt><x>145</x><y>47</y></pt><pt><x>145</x><y>242</y></pt><pt><x>131</x><y>242</y></pt></polygon></object><object><name>lighting,chandeliers</name><deleted>0</deleted><verified>0</verified><parts><hasparts></hasparts><ispartof></ispartof></parts><date>25-Jun-2017 05:15:14</date><id>1</id><type>bounding_box</type><polygon><username>anonymous</username><pt><x>154</x><y>257</y></pt><pt><x>379</x><y>257</y></pt><pt><x>379</x><y>351</y></pt><pt><x>154</x><y>351</y></pt></polygon></object><object><name>lighting,chandeliers</name><deleted>0</deleted><verified>0</verified><parts><hasparts></hasparts><ispartof></ispartof></parts><date>25-Jun-2017 05:15:27</date><id>2</id><type>bounding_box</type><polygon><username>anonymous</username><pt><x>143</x><y>25</y></pt><pt><x>381</x><y>25</y></pt><pt><x>381</x><y>170</y></pt><pt><x>143</x><y>170</y></pt></polygon></object><imagesize><nrows></nrows><ncols></ncols></imagesize></annotation>