<annotation><filename>3f81a64e0d9f8ca2_6483-w500-h400-b0-p0-traditional-living-room.jpg</filename><folder>living_room</folder><source><sourceImage>The MIT-CSAIL database of objects and scenes</sourceImage><sourceAnnotation>LabelMe Webtool</sourceAnnotation></source><object><name>window,medium</name><deleted>0</deleted><verified>0</verified><parts><hasparts></hasparts><ispartof></ispartof></parts><date>25-Jun-2017 08:41:07</date><id>0</id><type>bounding_box</type><polygon><username>anonymous</username><pt><x>94</x><y>98</y></pt><pt><x>231</x><y>98</y></pt><pt><x>231</x><y>290</y></pt><pt><x>94</x><y>290</y></pt></polygon></object><object><name>wallmaterial,granite</name><deleted>0</deleted><verified>0</verified><parts><hasparts></hasparts><ispartof></ispartof></parts><date>25-Jun-2017 08:41:42</date><id>1</id><type>bounding_box</type><polygon><username>anonymous</username><pt><x>376</x><y>46</y></pt><pt><x>617</x><y>46</y></pt><pt><x>617</x><y>192</y></pt><pt><x>376</x><y>192</y></pt></polygon></object><imagesize><nrows></nrows><ncols></ncols></imagesize></annotation>