<annotation><filename>ed617779037e058d_1981-w500-h400-b0-p0-modern-living-room.jpg</filename><folder>living_room</folder><source><sourceImage>The MIT-CSAIL database of objects and scenes</sourceImage><sourceAnnotation>LabelMe Webtool</sourceAnnotation></source><object><name>window,small</name><deleted>0</deleted><verified>0</verified><parts><hasparts></hasparts><ispartof></ispartof></parts><date>25-Jun-2017 10:43:58</date><id>0</id><type>bounding_box</type><polygon><username>anonymous</username><pt><x>206</x><y>96</y></pt><pt><x>493</x><y>96</y></pt><pt><x>493</x><y>250</y></pt><pt><x>206</x><y>250</y></pt></polygon></object><object><name>lighting,chandeliers</name><deleted>0</deleted><verified>0</verified><parts><hasparts></hasparts><ispartof></ispartof></parts><date>25-Jun-2017 10:44:11</date><id>1</id><type>bounding_box</type><polygon><username>anonymous</username><pt><x>567</x><y>241</y></pt><pt><x>604</x><y>241</y></pt><pt><x>604</x><y>282</y></pt><pt><x>567</x><y>282</y></pt></polygon></object><imagesize><nrows></nrows><ncols></ncols></imagesize></annotation>