<annotation><filename>ee01dcb70ff34163_7912-w500-h400-b0-p0-beach-style-living-room.jpg</filename><folder>living_room</folder><source><sourceImage>The MIT-CSAIL database of objects and scenes</sourceImage><sourceAnnotation>LabelMe Webtool</sourceAnnotation></source><object><name>fireplace,stone</name><deleted>0</deleted><verified>0</verified><parts><hasparts></hasparts><ispartof></ispartof></parts><date>25-Jun-2017 15:51:46</date><id>0</id><type>bounding_box</type><polygon><username>anonymous</username><pt><x>291</x><y>110</y></pt><pt><x>581</x><y>110</y></pt><pt><x>581</x><y>384</y></pt><pt><x>291</x><y>384</y></pt></polygon></object><object><name>wallmaterial,painted</name><deleted>0</deleted><verified>0</verified><parts><hasparts></hasparts><ispartof></ispartof></parts><date>25-Jun-2017 15:52:12</date><id>1</id><type>bounding_box</type><polygon><username>anonymous</username><pt><x>30</x><y>60</y></pt><pt><x>212</x><y>60</y></pt><pt><x>212</x><y>8</y></pt><pt><x>30</x><y>8</y></pt></polygon></object><imagesize><nrows></nrows><ncols></ncols></imagesize></annotation>