<annotation><filename>5181a3210491f814_1641-w500-h400-b0-p0-traditional-kitchen.jpg</filename><folder>kitchen</folder><source><sourceImage>The MIT-CSAIL database of objects and scenes</sourceImage><sourceAnnotation>LabelMe Webtool</sourceAnnotation></source><object><name>lighting,pendants</name><deleted>0</deleted><verified>0</verified><parts><hasparts></hasparts><ispartof></ispartof></parts><date>25-Jun-2017 03:31:12</date><id>0</id><type>bounding_box</type><polygon><username>anonymous</username><pt><x>123</x><y>138</y></pt><pt><x>275</x><y>138</y></pt><pt><x>275</x><y>2</y></pt><pt><x>123</x><y>2</y></pt></polygon></object><object><name>lighting,pendants</name><deleted>0</deleted><verified>0</verified><parts><hasparts></hasparts><ispartof></ispartof></parts><date>25-Jun-2017 03:31:28</date><id>1</id><type>bounding_box</type><polygon><username>anonymous</username><pt><x>313</x><y>137</y></pt><pt><x>430</x><y>137</y></pt><pt><x>430</x><y>5</y></pt><pt><x>313</x><y>5</y></pt></polygon></object><imagesize><nrows></nrows><ncols></ncols></imagesize></annotation>