<annotation><filename>c0d17c0a0834d1e1_9108-w500-h400-b0-p0-beach-style-dining-room.jpg</filename><folder>dining</folder><source><sourceImage>The MIT-CSAIL database of objects and scenes</sourceImage><sourceAnnotation>LabelMe Webtool</sourceAnnotation></source><object><name>lighting,chandeliers</name><deleted>0</deleted><verified>0</verified><parts><hasparts/><ispartof/></parts><date>26-Jun-2017 05:00:39</date><id>0</id><type>bounding_box</type><polygon><username>anonymous</username><pt><x>187</x><y>156</y></pt><pt><x>239</x><y>156</y></pt><pt><x>239</x><y>198</y></pt><pt><x>187</x><y>198</y></pt></polygon></object><object><name>countertop,stone</name><deleted>0</deleted><verified>0</verified><parts><hasparts/><ispartof/></parts><date>26-Jun-2017 05:01:05</date><id>1</id><type>bounding_box</type><polygon><username>anonymous</username><pt><x>293</x><y>263</y></pt><pt><x>606</x><y>263</y></pt><pt><x>606</x><y>319</y></pt><pt><x>293</x><y>319</y></pt></polygon></object><imagesize><nrows></nrows><ncols></ncols></imagesize><object><name>window,medium</name><deleted>0</deleted><verified>0</verified><parts><hasparts></hasparts><ispartof></ispartof></parts><date>26-Jun-2017 05:11:14</date><id>2</id><type>bounding_box</type><polygon><username>anonymous</username><pt><x>6</x><y>173</y></pt><pt><x>91</x><y>173</y></pt><pt><x>91</x><y>364</y></pt><pt><x>6</x><y>364</y></pt></polygon></object></annotation>